hdf5extractor/__init__.py
hdf5extractor/common.py
hdf5extractor/etp/__init__.py
hdf5extractor/etp/extract_etp.py
hdf5extractor/etp/requester.py
hdf5extractor/etp/server_protocols.py
hdf5extractor/etp/utils.py
hdf5extractor/etp/websocket_manager.py
hdf5extractor/extract_local.py
hdf5extractor/h5handler.py
hdf5extractor/main.py
hdf5extractor-1.0.4.dist-info/LICENSE
hdf5extractor-1.0.4.dist-info/METADATA
hdf5extractor-1.0.4.dist-info/WHEEL
hdf5extractor-1.0.4.dist-info/entry_points.txt
hdf5extractor-1.0.4.dist-info/RECORD
