Metadata-Version: 2.1
Name: hdf5extractor
Version: 1.0.4
Summary: Extract datasets from a h5 file, depending on referenced dataset from a xml file.
Home-page: http://www.geosiris.com
License: Apache-2.0
Keywords: Energyml,hdf,hdf5,resqml,osdu
Author: Valentin Gauthier
Author-email: valentin.gauthier@geosiris.com
Maintainer: Valentin Gauthier
Maintainer-email: valentin.gauthier@geosiris.com
Requires-Python: >=3.9,<4.0
Classifier: Development Status :: 4 - Beta
Classifier: Environment :: Web Environment
Classifier: Intended Audience :: Developers
Classifier: Intended Audience :: Information Technology
Classifier: License :: OSI Approved :: Apache Software License
Classifier: Operating System :: OS Independent
Classifier: Programming Language :: Python
Classifier: Programming Language :: Python :: 3
Classifier: Programming Language :: Python :: 3.9
Classifier: Programming Language :: Python :: 3.10
Classifier: Programming Language :: Python :: 3.11
Classifier: Programming Language :: Python :: 3.8
Classifier: Topic :: Internet
Classifier: Topic :: Internet :: WWW/HTTP
Classifier: Topic :: Software Development
Classifier: Topic :: Software Development :: Libraries
Classifier: Topic :: Software Development :: Libraries :: Application Frameworks
Classifier: Topic :: Software Development :: Libraries :: Python Modules
Classifier: Typing :: Typed
Requires-Dist: h5py (>=3.7.0,<4.0.0)
Requires-Dist: lxml (>=4.6.3,<5.0.0)
Requires-Dist: requests (>=2.25.1,<3.0.0)
Project-URL: Repository, https://github.com/geosiris-technologies/hdf5-extractor
